collective.messagesviewlet-0.23-nspkg.pth
collective/messagesviewlet/__init__.py
collective/messagesviewlet/configure.zcml
collective/messagesviewlet/interfaces.py
collective/messagesviewlet/message.py
collective/messagesviewlet/messagesconfig.py
collective/messagesviewlet/profiles.zcml
collective/messagesviewlet/setuphandlers.py
collective/messagesviewlet/subscribers.py
collective/messagesviewlet/testing.py
collective/messagesviewlet/testing.zcml
collective/messagesviewlet/upgrades.py
collective/messagesviewlet/utils.py
collective/messagesviewlet/browser/__init__.py
collective/messagesviewlet/browser/configure.zcml
collective/messagesviewlet/browser/messagesviewlet.pt
collective/messagesviewlet/browser/messagesviewlet.py
collective/messagesviewlet/browser/static/.gitkeep
collective/messagesviewlet/browser/static/chrome-24.png
collective/messagesviewlet/browser/static/firefox-24.png
collective/messagesviewlet/browser/static/hidemessageviewlet.js
collective/messagesviewlet/browser/static/js.cookie-2.0.3.min.js
collective/messagesviewlet/browser/static/message-icon.png
collective/messagesviewlet/browser/static/messagesviewlet.css
collective/messagesviewlet/browser/static/messagesviewlet.js
collective/messagesviewlet/browser/static/messagesviewlet.less
collective/messagesviewlet/locales/collective.messagesviewlet.pot
collective/messagesviewlet/locales/plone.pot
collective/messagesviewlet/locales/update.sh
collective/messagesviewlet/locales/en/LC_MESSAGES/collective.messagesviewlet.po
collective/messagesviewlet/locales/en/LC_MESSAGES/plone.po
collective/messagesviewlet/locales/fr/LC_MESSAGES/collective.messagesviewlet.po
collective/messagesviewlet/locales/fr/LC_MESSAGES/plone.po
collective/messagesviewlet/profiles/base/browserlayer.xml
collective/messagesviewlet/profiles/base/collectivemessagesviewlet_base.txt
collective/messagesviewlet/profiles/base/controlpanel.xml
collective/messagesviewlet/profiles/base/import_steps.xml
collective.messagesviewlet-0.23.dist-info/DESCRIPTION.rst
collective.messagesviewlet-0.23.dist-info/METADATA
collective.messagesviewlet-0.23.dist-info/RECORD
collective.messagesviewlet-0.23.dist-info/WHEEL
collective.messagesviewlet-0.23.dist-info/entry_points.txt
collective.messagesviewlet-0.23.dist-info/metadata.json
collective.messagesviewlet-0.23.dist-info/namespace_packages.txt
collective.messagesviewlet-0.23.dist-info/top_level.txt
