Metadata-Version: 2.0
Name: collective.messagesviewlet
Version: 0.23
Summary: Add-on displaying manager defined messages in a viewlet
Home-page: http://pypi.python.org/pypi/collective.messagesviewlet
Author: IMIO Team
Author-email: support@imio.be
License: GPL version 2
Keywords: Python Plone
Platform: UNKNOWN
Classifier: Environment :: Web Environment
Classifier: Framework :: Plone
Classifier: Framework :: Plone :: 4.3
Classifier: Framework :: Plone :: Addon
Classifier: Programming Language :: Python
Classifier: Programming Language :: Python :: 2.7
Classifier: Operating System :: OS Independent
Classifier: License :: OSI Approved :: GNU General Public License v2 (GPLv2)
Provides-Extra: plone4
Provides-Extra: test
Requires-Dist: collective.behavior.talcondition
Requires-Dist: setuptools
Provides-Extra: plone4
Requires-Dist: plone.api; extra == 'plone4'
Requires-Dist: plone.app.contenttypes; extra == 'plone4'
Requires-Dist: plone.app.dexterity; extra == 'plone4'
Requires-Dist: plone.app.lockingbehavior; extra == 'plone4'
Requires-Dist: plone.formwidget.datetime (>=1.2); extra == 'plone4'
Provides-Extra: test
Requires-Dist: plone.app.robotframework[debug]; extra == 'test'
Requires-Dist: plone.app.testing; extra == 'test'
Requires-Dist: robotframework-selenium2screenshots; extra == 'test'
